[
  {
    "expr": "Id=2033059188",
    "entities": [
      {
        "logprob": -12.419,
        "Id": 2033059188
      }
    ]
  },

  {
    "expr": "Id=2147152072",
    "entities": [
      {
        "logprob": -15.513,
        "Id": 2147152072,
        "AA": [
          {
            "AuId": 2033059188,
            "AfId": 40347166
          },
          {
            "AuId": 676500258
          },
          {
            "AuId": 2019832499
          },
          {
            "AuId": 2114332599
          },
          {
            "AuId": 2004554093,
            "AfId": 125749732
          }
        ],
        "F": [
          {
            "FId": 170133592
          },
          {
            "FId": 56666940
          },
          {
            "FId": 22789450
          },
          {
            "FId": 10879293
          },
          {
            "FId": 186311912
          },
          {
            "FId": 124246873
          },
          {
            "FId": 23123220
          },
          {
            "FId": 105795698
          },
          {
            "FId": 41008148
          }
        ],
        "J": {
          "JId": 135954941
        }
      }
    ]
  },

  {
    "expr": "Composite(AA.AuId=2033059188)",
    "entities": [
      {
        "logprob": -15.513,
        "Id": 2147152072,
        "AA": [
          {
            "AuId": 2033059188,
            "AfId": 40347166
          },
          {
            "AuId": 676500258
          },
          {
            "AuId": 2019832499
          },
          {
            "AuId": 2114332599
          },
          {
            "AuId": 2004554093,
            "AfId": 125749732
          }
        ],
        "F": [
          {
            "FId": 170133592
          },
          {
            "FId": 56666940
          },
          {
            "FId": 22789450
          },
          {
            "FId": 10879293
          },
          {
            "FId": 186311912
          },
          {
            "FId": 124246873
          },
          {
            "FId": 23123220
          },
          {
            "FId": 105795698
          },
          {
            "FId": 41008148
          }
        ],
        "J": {
          "JId": 135954941
        }
      },
      {
        "logprob": -18.671,
        "Id": 2091273188,
        "AA": [
          {
            "AuId": 676500258
          },
          {
            "AuId": 2019832499
          },
          {
            "AuId": 2114332599
          },
          {
            "AuId": 2033059188,
            "AfId": 40347166
          },
          {
            "AuId": 2004554093,
            "AfId": 125749732
          }
        ],
        "F": [
          {
            "FId": 146172628
          },
          {
            "FId": 170133592
          },
          {
            "FId": 22789450
          },
          {
            "FId": 169896238
          },
          {
            "FId": 107457646
          },
          {
            "FId": 41008148
          }
        ],
        "C": {
          "CId": 1163450153
        }
      },
      {
        "logprob": -19.083,
        "Id": 2093432797,
        "AA": [
          {
            "AuId": 2019832499
          },
          {
            "AuId": 2033059188,
            "AfId": 40347166
          },
          {
            "AuId": 676500258
          },
          {
            "AuId": 2114332599
          },
          {
            "AuId": 2004554093,
            "AfId": 125749732
          },
          {
            "AuId": 733523630
          },
          {
            "AuId": 1984415179
          }
        ],
        "F": [
          {
            "FId": 22789450
          },
          {
            "FId": 169896238
          },
          {
            "FId": 23123220
          },
          {
            "FId": 41008148
          }
        ],
        "C": {
          "CId": 1140684652
        }
      },
      {
        "logprob": -19.616,
        "Id": 195445992,
        "AA": [
          {
            "AuId": 2033059188
          },
          {
            "AuId": 676500258
          },
          {
            "AuId": 2019832499
          },
          {
            "AuId": 2114332599
          },
          {
            "AuId": 2004554093
          }
        ],
        "F": [
          {
            "FId": 146172628
          },
          {
            "FId": 186311912
          },
          {
            "FId": 41008148
          }
        ],
        "J": {
          "JId": 80113298
        }
      },
      {
        "logprob": -19.996,
        "Id": 206359983,
        "AA": [
          {
            "AuId": 676500258
          },
          {
            "AuId": 2019832499
          },
          {
            "AuId": 2114332599
          },
          {
            "AuId": 2033059188
          }
        ],
        "F": [
          {
            "FId": 170133592
          },
          {
            "FId": 41008148
          }
        ],
        "C": {
          "CId": 1163450153
        }
      },
      {
        "logprob": -21.86,
        "Id": 100437579,
        "AA": [
          {
            "AuId": 2033059188
          },
          {
            "AuId": 676500258
          },
          {
            "AuId": 2114332599
          },
          {
            "AuId": 428293613
          },
          {
            "AuId": 2122254668
          }
        ]
      },
      {
        "logprob": -21.964,
        "Id": 115648301,
        "AA": [
          {
            "AuId": 2033059188
          },
          {
            "AuId": 676500258
          },
          {
            "AuId": 2019832499
          }
        ],
        "F": [
          {
            "FId": 170133592
          },
          {
            "FId": 186311912
          },
          {
            "FId": 41008148
          }
        ],
        "J": {
          "JId": 80113298
        }
      },
      {
        "logprob": -22.139,
        "Id": 112686118,
        "AA": [
          {
            "AuId": 2033059188
          },
          {
            "AuId": 676500258
          },
          {
            "AuId": 428293613
          },
          {
            "AuId": 2114332599
          },
          {
            "AuId": 2004554093
          }
        ],
        "F": [
          {
            "FId": 179328971
          },
          {
            "FId": 186311912
          },
          {
            "FId": 41008148
          }
        ],
        "J": {
          "JId": 80113298
        }
      },
      {
        "logprob": -22.75,
        "Id": 1967588330,
        "AA": [
          {
            "AuId": 2304872535,
            "AfId": 40347166
          },
          {
            "AuId": 1999734350,
            "AfId": 40347166
          },
          {
            "AuId": 2033059188,
            "AfId": 40347166
          }
        ],
        "C": {
          "CId": 1140684652
        }
      },
      {
        "logprob": -22.764,
        "Id": 2010377209,
        "AA": [
          {
            "AuId": 2144856130,
            "AfId": 40347166
          },
          {
            "AuId": 1999734350,
            "AfId": 40347166
          },
          {
            "AuId": 2033059188,
            "AfId": 40347166
          }
        ],
        "F": [
          {
            "FId": 41008148
          }
        ],
        "J": {
          "JId": 6756005
        }
      },
      {
        "logprob": -23.807,
        "Id": 2331883746,
        "AA": [
          {
            "AuId": 2033059188
          }
        ],
        "J": {
          "JId": 174847851
        }
      }
    ]
  },

  {
    "expr": "Composite(AA.AuId=2147152072)",
    "entities": []
  }

]